pushbaby
