Metadata-Version: 1.1
Name: pushbaby
Version: 0.0.4
Summary: APNS library using gevent
Home-page: https://github.com/matrix-org/pushbaby
Author: matrix.org
Author-email: dave@matrix.org
License: Apache License, Version 2.0
Keywords: apns push
Platform: UNKNOWN
Classifier: Development Status :: 3 - Alpha
Classifier: Intended Audience :: Developers
Classifier: License :: OSI Approved :: Apache Software License
Classifier: Programming Language :: Python :: 2
